LICENSE.txt
MANIFEST.in
README.md
package.json
setup.py
dash_uploader/__init__.py
dash_uploader/callbacks.py
dash_uploader/configure_upload.py
dash_uploader/httprequesthandler.py
dash_uploader/settings.py
dash_uploader/upload.py
dash_uploader/utils.py
dash_uploader.egg-info/PKG-INFO
dash_uploader.egg-info/SOURCES.txt
dash_uploader.egg-info/dependency_links.txt
dash_uploader.egg-info/requires.txt
dash_uploader.egg-info/top_level.txt
dash_uploader/_build/Button.py
dash_uploader/_build/ProgressBar.py
dash_uploader/_build/Upload_ReactComponent.py
dash_uploader/_build/__init__.py
dash_uploader/_build/_imports_.py
dash_uploader/_build/dash_uploader.min.js
dash_uploader/_build/dash_uploader.min.js.map
dash_uploader/_build/metadata.json
dash_uploader/_build/package-info.json
docs/README-PyPi.md
tests/test_disabled.py
tests/test_usage.py