Metadata-Version: 2.1
Name: dash_uploader
Version: 0.6.1
Summary: Upload large files using resumable.js
Home-page: https://github.com/np-8/dash-uploader
Author: Niko Pasanen <niko@pasanen.me>
Author-email: niko@pasanen.me
License: MIT
Classifier: Framework :: Dash
License-File: LICENSE.txt
Requires-Dist: dash>=1.1.0
Provides-Extra: dev
Requires-Dist: pyyaml~=5.3.1; extra == "dev"
